codemate/__init__.py
codemate/ai.py
codemate/api_manager.py
codemate/cli.py
codemate/func.py
codemate/process.py
codesmate-0.1.0.dist-info/METADATA
codesmate-0.1.0.dist-info/WHEEL
codesmate-0.1.0.dist-info/entry_points.txt
codesmate-0.1.0.dist-info/licenses/LICENSE
codesmate-0.1.0.dist-info/RECORD
