Metadata-Version: 2.4
Name: codesmate
Version: 0.1.0
Summary: AI Assistant CLI for debugging and refactoring code
Project-URL: Repository, https://github.com/MahdiMirshafiee/codemate
Project-URL: Issues, https://github.com/MahdiMirshafiee/codemate/issues
Author-email: Mahdi Mirshafiee <mirshafieemahdi001@gmail.com>, Saleh Mirshafiee <seyed82saleh@gmail.com>
License: MIT
License-File: LICENSE
Keywords: ai,assistant,cli,debug,refactor
Classifier: Development Status :: 3 - Alpha
Classifier: Intended Audience :: Developers
Classifier: License :: OSI Approved :: MIT License
Classifier: Operating System :: OS Independent
Classifier: Programming Language :: Python :: 3
Classifier: Programming Language :: Python :: 3.8
Classifier: Programming Language :: Python :: 3.9
Classifier: Programming Language :: Python :: 3.10
Classifier: Programming Language :: Python :: 3.11
Classifier: Programming Language :: Python :: 3.12
Classifier: Topic :: Software Development :: Debuggers
Classifier: Topic :: Software Development :: Quality Assurance
Requires-Python: >=3.8
Requires-Dist: openai>=1.0.0
Requires-Dist: rich>=10.0.0
